buddybet_idpsecure/__init__.py
buddybet_idpsecure/authorization/__init__.py
buddybet_idpsecure/authorization/fastAPI_auth.py
buddybet_idpsecure/authorization/transaction_auth.py
buddybet_idpsecure/core/__init__.py
buddybet_idpsecure/core/environment_config.py
buddybet_idpsecure/core/idp_constants.py
buddybet_idpsecure/core/settings_config.py
buddybet_idpsecure/model/__init__.py
buddybet_idpsecure/model/user_claims.py
buddybet_idpsecure/resources/env_dev.yaml
buddybet_idpsecure/resources/env_local.yaml
buddybet_idpsecure/resources/env_pre.yaml
buddybet_idpsecure/resources/env_pro.yaml
buddybet_idpsecure/validation/__init__.py
buddybet_idpsecure/validation/exceptions.py
buddybet_idpsecure/validation/jwks.py
buddybet_idpsecure/validation/validator.py
buddybet_idpsecure-1.0.8.dist-info/METADATA
buddybet_idpsecure-1.0.8.dist-info/WHEEL
buddybet_idpsecure-1.0.8.dist-info/RECORD
