Metadata-Version: 2.3
Name: buddybet_idpsecure
Version: 1.0.8
Summary: Secure in validate JWT Token
Keywords: jwt,jwks,fastapi,authentication,security
Author: ricardomarzochi07
Author-email: ricardomarzochi@gmail.com
Requires-Python: >=3.12
Classifier: Programming Language :: Python :: 3
Classifier: Programming Language :: Python :: 3.12
Classifier: Programming Language :: Python :: 3.13
Requires-Dist: buddybet-logmon-common (>=0.1.0,<0.2.0)
Requires-Dist: jwt (>=1.4.0,<2.0.0)
Requires-Dist: pyjwt (>=2.10.1,<3.0.0)
Requires-Dist: python-jose (>=3.5.0,<4.0.0)
Requires-Dist: pyyaml (>=6.0.2,<7.0.0)
